odoo/addons/odoo_opentelemetry_distro/__init__.py
odoo/addons/odoo_opentelemetry_distro/__manifest__.py
odoo/addons/otel_odoo_base/__init__.py
odoo/addons/otel_odoo_base/__manifest__.py
odoo/addons/otel_odoo_base/controller/__init__.py
odoo/addons/otel_odoo_base/controller/otel_health.py
odoo/addons/otel_odoo_base/otel_14/__init__.py
odoo/addons/otel_odoo_base/otel_14/web_controller.py
odoo/addons/otel_odoo_base/otel_15/__init__.py
odoo/addons/otel_odoo_base/otel_16/__init__.py
odoo/addons/otel_odoo_base/otel_16/web_controller.py
odoo/addons/otel_odoo_base/otel_17/__init__.py
odoo/addons/otel_odoo_base/otel_17/web_controller.py
odoo/addons/otel_odoo_base/otel_18/__init__.py
odoo/addons/otel_odoo_base/otel_base/__init__.py
odoo/addons/otel_odoo_base/otel_base/abstract_base.py
odoo/addons/otel_odoo_base/otel_base/abstract_base.pyi
odoo/addons/otel_odoo_base/otel_base/ir_cron.py
odoo/addons/otel_odoo_base/otel_base/ir_mail_server.py
odoo/addons/otel_odoo_base/otel_base/ir_report.py
odoo/addons/otel_odoo_base/tests/__init__.py
odoo/addons/otel_odoo_base/tests/case.py
odoo/addons/otel_odoo_base/tests/test_metrics.py
odoo/addons/otel_odoo_queue_job/__init__.py
odoo/addons/otel_odoo_queue_job/__manifest__.py
odoo/addons/otel_odoo_queue_job/controller.py
opentelemetry_distro_odoo/__init__.py
opentelemetry_distro_odoo/odoo_metrics.py
opentelemetry_distro_odoo/otel_test.py
opentelemetry_distro_odoo/utils.py
opentelemetry_distro_odoo/version.py
opentelemetry_distro_odoo/distro/__init__.py
opentelemetry_distro_odoo/distro/_loader.py
opentelemetry_distro_odoo/distro/odoo.py
opentelemetry_distro_odoo/instrumentation/__init__.py
opentelemetry_distro_odoo/instrumentation/odoo.py
opentelemetry_distro_odoo/instrumentation/odoo_system.py
opentelemetry_distro_odoo/instrumentation/pre_otel_system.py
opentelemetry_distro_odoo/resource/__init__.py
opentelemetry_distro_odoo/resource/clevercloud.py
opentelemetry_distro_odoo/resource/odoo.py
opentelemetry_distro_odoo/semconv/__init__.py
opentelemetry_distro_odoo-0.1.3.dist-info/METADATA
opentelemetry_distro_odoo-0.1.3.dist-info/WHEEL
opentelemetry_distro_odoo-0.1.3.dist-info/entry_points.txt
opentelemetry_distro_odoo-0.1.3.dist-info/RECORD
