Metadata-Version: 2.4
Name: opentelemetry-distro-odoo
Version: 0.1.3
Summary: OpenTelemetry Python SDK
Author-email: OpenTelemetry Authors <cncf-opentelemetry-contributors@lists.cncf.io>
License-Expression: Apache-2.0
Classifier: Development Status :: 5 - Production/Stable
Classifier: Framework :: Odoo
Classifier: Framework :: Odoo :: 12.0
Classifier: Framework :: Odoo :: 13.0
Classifier: Framework :: Odoo :: 14.0
Classifier: Framework :: Odoo :: 15.0
Classifier: Framework :: Odoo :: 16.0
Classifier: Framework :: Odoo :: 17.0
Classifier: Framework :: Odoo :: 18.0
Classifier: Framework :: OpenTelemetry
Classifier: Intended Audience :: Developers
Classifier: Programming Language :: Python
Classifier: Programming Language :: Python :: 3
Classifier: Programming Language :: Python :: 3.9
Classifier: Programming Language :: Python :: 3.10
Classifier: Programming Language :: Python :: 3.11
Classifier: Programming Language :: Python :: 3.12
Classifier: Programming Language :: Python :: 3.13
Classifier: Typing :: Typed
Requires-Python: >=3.8
Requires-Dist: opentelemetry-api~=1.33.1; python_version < '3.9'
Requires-Dist: opentelemetry-api~=1.34.1; python_version >= '3.9'
Requires-Dist: opentelemetry-distro~=0.54b1; python_version < '3.9'
Requires-Dist: opentelemetry-distro~=0.55b1; python_version >= '3.9'
Requires-Dist: opentelemetry-exporter-otlp-proto-http~=1.33.1; python_version < '3.9'
Requires-Dist: opentelemetry-exporter-otlp-proto-http~=1.34.1; python_version >= '3.9'
Requires-Dist: opentelemetry-instrumentation-wsgi~=0.54b1; python_version < '3.9'
Requires-Dist: opentelemetry-instrumentation-wsgi~=0.55b1; python_version >= '3.9'
Requires-Dist: opentelemetry-sdk~=1.33.1; python_version < '3.9'
Requires-Dist: opentelemetry-sdk~=1.34.1; python_version >= '3.9'
Requires-Dist: opentelemetry-test-utils==0.54b1; python_version < '3.9'
Requires-Dist: opentelemetry-test-utils>=0.55b1; python_version >= '3.9'
Requires-Dist: typing-extensions>=4.5.0
Requires-Dist: wrapt>=1.14.1
Provides-Extra: instruments
Requires-Dist: opentelemetry-instrumentation-psycopg2~=0.54b1; (python_version < '3.9') and extra == 'instruments'
Requires-Dist: opentelemetry-instrumentation-psycopg2~=0.55b1; (python_version >= '3.9') and extra == 'instruments'
Requires-Dist: opentelemetry-instrumentation-requests~=0.54b1; (python_version < '3.9') and extra == 'instruments'
Requires-Dist: opentelemetry-instrumentation-requests~=0.55b1; (python_version >= '3.9') and extra == 'instruments'
Requires-Dist: opentelemetry-instrumentation-system-metrics~=0.54b1; (python_version < '3.9') and extra == 'instruments'
Requires-Dist: opentelemetry-instrumentation-system-metrics~=0.55b1; (python_version >= '3.9') and extra == 'instruments'
Provides-Extra: logfmt
Requires-Dist: logfmter~=0.0.8; (python_version < '3.9') and extra == 'logfmt'
Requires-Dist: logfmter~=0.0.9; (python_version >= '3.9') and extra == 'logfmt'
Provides-Extra: proto-grpc
Requires-Dist: opentelemetry-exporter-otlp-proto-grpc~=1.33.1; (python_version < '3.9') and extra == 'proto-grpc'
Requires-Dist: opentelemetry-exporter-otlp-proto-grpc~=1.34.1; (python_version >= '3.9') and extra == 'proto-grpc'
Provides-Extra: proto-http
